chapyter/__init__.py
chapyter/_version.py
chapyter/magic.py
chapyter/programs.py
chapyter-0.3.1.data/data/share/jupyter/labextensions/@shannon-shen/chapyter/package.json
chapyter-0.3.1.data/data/share/jupyter/labextensions/@shannon-shen/chapyter/schemas/@shannon-shen/chapyter/package.json.orig
chapyter-0.3.1.data/data/share/jupyter/labextensions/@shannon-shen/chapyter/static/568.963fc68e9aea61cb1c90.js
chapyter-0.3.1.data/data/share/jupyter/labextensions/@shannon-shen/chapyter/static/747.217e756827eb66a6f3d4.js
chapyter-0.3.1.data/data/share/jupyter/labextensions/@shannon-shen/chapyter/static/remoteEntry.fa1a7e093e0f27eb2386.js
chapyter-0.3.1.data/data/share/jupyter/labextensions/@shannon-shen/chapyter/static/style.js
chapyter-0.3.1.data/data/share/jupyter/labextensions/@shannon-shen/chapyter/static/third-party-licenses.json
chapyter-0.3.1.data/data/share/jupyter/labextensions/@shannon-shen/chapyter/install.json
chapyter-0.3.1.dist-info/METADATA
chapyter-0.3.1.dist-info/WHEEL
chapyter-0.3.1.dist-info/licenses/LICENSE
chapyter-0.3.1.dist-info/RECORD
