Metadata-Version: 2.1
Name: chapyter
Version: 0.3.1
Summary: A Natural Language-Based Python Program Interpreter
Project-URL: Homepage, https://github.com/chapyter/chapyter
Project-URL: Bug Tracker, https://github.com/chapyter/chapyter/issues
Project-URL: Repository, https://github.com/chapyter/chapyter.git
Author-email: chapyter <zejiangshen@gmail.com>
License: BSD 3-Clause License
License-File: LICENSE
Classifier: Framework :: Jupyter
Classifier: Framework :: Jupyter :: JupyterLab
Classifier: Framework :: Jupyter :: JupyterLab :: 4
Classifier: Framework :: Jupyter :: JupyterLab :: Extensions
Classifier: Framework :: Jupyter :: JupyterLab :: Extensions :: Prebuilt
Classifier: License :: OSI Approved :: BSD License
Classifier: Programming Language :: Python
Classifier: Programming Language :: Python :: 3
Classifier: Programming Language :: Python :: 3.8
Classifier: Programming Language :: Python :: 3.9
Classifier: Programming Language :: Python :: 3.10
Classifier: Programming Language :: Python :: 3.11
Requires-Python: >=3.8
Requires-Dist: guidance
Requires-Dist: jupyterlab>=4.0
Requires-Dist: python-dotenv
